Targets/__init__.py
models/__init__.py
models/application.py
models/plugins.py
models/targets.py
sego_cli-0.1.0.0.dist-info/LICENSE
sego_cli-0.1.0.0.dist-info/METADATA
sego_cli-0.1.0.0.dist-info/WHEEL
sego_cli-0.1.0.0.dist-info/top_level.txt
sego_cli-0.1.0.0.dist-info/RECORD
